{
	"sidetabs.description": "Afficher les onglets de l'éditeur verticalement dans la barre latérale.",
	"sidetabs.viewContainers.title": "Onglets latéraux",
	"sidetabs.views.name": "Onglets latéraux",
	"sidetabs.viewsWelcome.contents": "Aucun onglet ouvert.\nOuvrez un fichier pour le voir ici.",
	"sidetabs.command.closeTab.title": "Onglets latéraux : Fermer l'onglet",
	"sidetabs.command.closeOtherTabs.title": "Onglets latéraux : Fermer les autres onglets",
	"sidetabs.command.closeAllTabs.title": "Onglets latéraux : Fermer tous les onglets",
	"sidetabs.command.showTabMenu.title": "Onglets latéraux : Afficher le menu des onglets",
	"sidetabs.config.title": "Onglets latéraux",
	"sidetabs.config.fontSize.description": "Taille de la police des onglets (en pixels)",
	"sidetabs.config.tabHeight.description": "Hauteur des onglets (en pixels)",
	"sidetabs.config.showDirectoryPath.description": "Afficher le chemin du répertoire du fichier à côté du nom",
	"sidetabs.config.enableCopilotIntegration.description": "Afficher les indicateurs d'activité GitHub Copilot sur les onglets",
	"sidetabs.quickPick.close": "Fermer",
	"sidetabs.quickPick.close.description": "Fermer cet onglet",
	"sidetabs.quickPick.closeOther": "Fermer les autres",
	"sidetabs.quickPick.closeOther.description": "Fermer tous les onglets sauf celui-ci",
	"sidetabs.quickPick.closeAll": "Fermer tous",
	"sidetabs.quickPick.closeAll.description": "Fermer tous les onglets",
	"sidetabs.quickPick.separator": "Séparateur",
	"sidetabs.quickPick.split": "Diviser l'éditeur",
	"sidetabs.quickPick.split.description": "Diviser l'éditeur avec cet onglet",
	"sidetabs.quickPick.copyPath": "Copier le chemin",
	"sidetabs.quickPick.copyPath.description": "Copier le chemin du fichier dans le presse-papiers",
	"sidetabs.quickPick.placeholder": "Actions pour {0}",
	"sidetabs.info.pathCopied": "Chemin copié dans le presse-papiers",
	"sidetabs.error.loadingView": "Erreur lors du chargement de SideTabs",
	"sidetabs.tooltip.copilotActive": "GitHub Copilot travaille sur ce fichier",
	"sidetabs.tooltip.copilotSuggestion": "GitHub Copilot a des modifications en attente"
}